MANIFEST.in
setup.py
bootstrap/__init__.py
bootstrap/static/bootstrap/css/bootstrap-theme.css
bootstrap/static/bootstrap/css/bootstrap-theme.min.css
bootstrap/static/bootstrap/css/bootstrap.css
bootstrap/static/bootstrap/css/bootstrap.min.css
bootstrap/static/bootstrap/fonts/glyphicons-halflings-regular.eot
bootstrap/static/bootstrap/fonts/glyphicons-halflings-regular.svg
bootstrap/static/bootstrap/fonts/glyphicons-halflings-regular.ttf
bootstrap/static/bootstrap/fonts/glyphicons-halflings-regular.woff
bootstrap/static/bootstrap/img/glyphicons-halflings-white.png
bootstrap/static/bootstrap/img/glyphicons-halflings.png
bootstrap/static/bootstrap/js/bootstrap.js
bootstrap/static/bootstrap/js/bootstrap.min.js
bootstrap/static/bootstrap/less/accordion.less
bootstrap/static/bootstrap/less/alerts.less
bootstrap/static/bootstrap/less/badges.less
bootstrap/static/bootstrap/less/bootstrap.less
bootstrap/static/bootstrap/less/breadcrumbs.less
bootstrap/static/bootstrap/less/button-groups.less
bootstrap/static/bootstrap/less/buttons.less
bootstrap/static/bootstrap/less/carousel.less
bootstrap/static/bootstrap/less/close.less
bootstrap/static/bootstrap/less/code.less
bootstrap/static/bootstrap/less/component-animations.less
bootstrap/static/bootstrap/less/dropdowns.less
bootstrap/static/bootstrap/less/forms.less
bootstrap/static/bootstrap/less/glyphicons.less
bootstrap/static/bootstrap/less/grid.less
bootstrap/static/bootstrap/less/input-groups.less
bootstrap/static/bootstrap/less/jumbotron.less
bootstrap/static/bootstrap/less/labels.less
bootstrap/static/bootstrap/less/list-group.less
bootstrap/static/bootstrap/less/media.less
bootstrap/static/bootstrap/less/mixins.less
bootstrap/static/bootstrap/less/modals.less
bootstrap/static/bootstrap/less/navbar.less
bootstrap/static/bootstrap/less/navs.less
bootstrap/static/bootstrap/less/normalize.less
bootstrap/static/bootstrap/less/pager.less
bootstrap/static/bootstrap/less/pagination.less
bootstrap/static/bootstrap/less/panels.less
django_bootstrap_static_files.egg-info/PKG-INFO
django_bootstrap_static_files.egg-info/SOURCES.txt
django_bootstrap_static_files.egg-info/dependency_links.txt
django_bootstrap_static_files.egg-info/not-zip-safe
django_bootstrap_static_files.egg-info/top_level.txt