Metadata-Version: 1.0
Name: django-bootstrap-static-files
Version: 3.0.0
Summary: Twitter bootstrap static files for Django.
Home-page: https://github.com/ashchristopher/django-bootstrap-static-files
Author: Ash Christopher
Author-email: ash.christopher@gmail.com
License: Apache License 2.0
Platform: UNKNOWN
Classifier: Development Status :: 5 - Production/Stable
Classifier: Environment :: Web Environment
Classifier: Intended Audience :: Developers
Classifier: Operating System :: OS Independent
Classifier: Programming Language :: Python
Classifier: Framework :: Django
